{
  "errors": [
    {
      "code": -1,
      "enMsg": "UnknownError",
      "zhMsg": "位置错误",
      "reasons": []
    },
    {
      "code": 70002,
      "enMsg": "Seat index not correct",
      "zhMsg": "目标麦位不存在",
      "reasons": [
        "1、确保麦位索引大于0，小于最大麦位数",
        "2、确保当前房间已通过createAndJoinRoom创建成功",
        "3、检查麦位变更回调是否正常，如麦位集合为空，请联系我们"
      ]
    },
    {
      "code": 70003,
      "enMsg": "Already on seat",
      "zhMsg": "当前用户或所抱上麦的用户已在麦上",
      "reasons": [
        "1、如：enterSeat，请确保当前当前用户未上麦，如当前户已上麦，可以使用switchSeatTo实现跳麦",
        "2、如：pickUserToSeat，请确保所抱的用户未上麦，已上麦的用户不能被抱上麦"
      ]
    },
    {
      "code": 70004,
      "enMsg": "User not on seat",
      "zhMsg": "当前用户或所抱上麦的用户已在麦上",
      "reasons": [
        "1、如是switchSeatTo，请确保当前用户已上麦，如当前用户未上麦，可以使用enterSeat实现上麦",
        "2、如果kickUserFromSeat，请确保所踢的用户已上麦，未上麦的用户不能被踢"
      ]
    },
    {
      "code": 70005,
      "enMsg": "Target seat index can't equal to current index",
      "zhMsg": "当前操作的目标麦位不可用，",
      "reasons": [
        "1、请确保跳麦的目标麦位和当前麦位不是同一个麦位"
      ]
    },
    {
      "code": 70006,
      "enMsg": "Target Seat is locked or using",
      "zhMsg": "当前操作的目标麦位不可用，",
      "reasons": [
        "1、确保目标麦位为非锁定状态",
        "2、确保目标麦位为空闲状态"
      ]
    },
    {
      "code": 70007,
      "enMsg": "Can't pick self on seat",
      "zhMsg": "当前被抱上麦的用户是当前用户自己",
      "reasons": [
        "1、确保所抱上麦的用户非当前用户，自己不能抱自己上麦"
      ]
    },
    {
      "code": 70008,
      "enMsg": "Pick user failed",
      "zhMsg": "上麦邀请失败",
      "reasons": [
        "1、请确保当前已加入房间成功",
        "2、请参考底层错误信息解决(RCVoiceRoomError nativeErrorMessage)"
      ]
    },
    {
      "code": 70009,
      "enMsg": "Can't kick self",
      "zhMsg": "当前被踢下麦的用户是当前用户自己",
      "reasons": [
        "1、确保被踢下麦的用户不是当前用户，自己不能踢自己下麦"
      ]
    },
    {
      "code": 70010,
      "enMsg": "Join room failed",
      "zhMsg": "加入房间失败",
      "reasons": [
        "1、请确保当前用户已通过createAndJoinRoom创建成功",
        "2、请参考底层错误信息解决(RCVoiceRoomError nativeErrorMessage)"
      ]
    },
    {
      "code": 70011,
      "enMsg": "Leave room failed",
      "zhMsg": "离开房间失败",
      "reasons": [
        "1、请确保当前已加入房间成功",
        "2、请参考底层错误信息解决(RCVoiceRoomError nativeErrorMessage)"
      ]
    },
    {
      "code": 70012,
      "enMsg": "Get room info failed",
      "zhMsg": "获取房间信息失败",
      "reasons": []
    },
    {
      "code": 70013,
      "enMsg": "Already request seat",
      "zhMsg": "当前用户已经申请上麦",
      "reasons": [
        "1、请确保当前用户未申请上麦，如已申请，可通过cancelRequestSeat()来取消申请",
        "2、请参考底层错误信息解决(RCVoiceRoomError nativeErrorMessage)"
      ]
    },
    {
      "code": 70014,
      "enMsg": "Request seat list is full, the max is 20",
      "zhMsg": "当前未被处理的申请上麦请求，已达到最大限制20",
      "reasons": [
        "1、通过acceptRequestSeat()或rejectRequestSeat()去处理上麦请求，减少未处理的上麦请求"
      ]
    },
    {
      "code": 70015,
      "enMsg": "Request seat failed",
      "zhMsg": "申请上麦失败",
      "reasons": [
        "1、请参考底层错误信息解决(RCVoiceRoomError nativeErrorMessage)"
      ]
    },
    {
      "code": 70016,
      "enMsg": "Cancel request seat failed",
      "zhMsg": "上麦申请取消失败",
      "reasons": [
        "1、请参考底层错误信息解决(RCVoiceRoomError nativeErrorMessage)"
      ]
    },
    {
      "code": 70017,
      "enMsg": "Accept request seat failed",
      "zhMsg": "接受上麦申请失败",
      "reasons": [
        "1、请参考底层错误信息解决(RCVoiceRoomError nativeErrorMessage)"
      ]
    },
    {
      "code": 70018,
      "enMsg": "Reject request seat failed",
      "zhMsg": "拒绝上麦申请失败",
      "reasons": [
        "1、请参考底层错误信息解决(RCVoiceRoomError nativeErrorMessage)"
      ]
    },
    {
      "code": 70019,
      "enMsg": "Update seat info failed",
      "zhMsg": "麦位信息更新失败",
      "reasons": [
        "1、请参考底层错误信息解决(RCVoiceRoomError nativeErrorMessage)"
      ]
    },
    {
      "code": 70020,
      "enMsg": "Update room Info failed",
      "zhMsg": "房间信息更新失败",
      "reasons": [
        "1、请参考底层错误信息解决(RCVoiceRoomError nativeErrorMessage)"
      ]
    },
    {
      "code": 70021,
      "enMsg": "Get seat list failed",
      "zhMsg": "麦位信息列表获取失败",
      "reasons": [
        "1、请参考底层错误信息解决(RCVoiceRoomError nativeErrorMessage)"
      ]
    },
    {
      "code": 70022,
      "enMsg": "Get request seat list failed",
      "zhMsg": "申请麦位列表集合获取失败",
      "reasons": [
        "1、请确保已在房间内",
        "2、请参考底层错误信息解决(RCVoiceRoomError nativeErrorMessage)"
      ]
    },
    {
      "code": 70023,
      "enMsg": "Send message failed",
      "zhMsg": "房间消息发送失败",
      "reasons": [
        "1、请确保已在房间内",
        "2、请参考底层错误信息解决(RCVoiceRoomError nativeErrorMessage)"
      ]
    },
    {
      "code": 70024,
      "enMsg": "Invitation failed",
      "zhMsg": "自定义邀请失败",
      "reasons": [
        "1、请确保已在房间内",
        "2、请参考底层错误信息解决(RCVoiceRoomError nativeErrorMessage)"
      ]
    },
    {
      "code": 70025,
      "enMsg": "Cancel invitation failed",
      "zhMsg": "取消自定义邀请失败",
      "reasons": [
        "1、请确保已在房间内",
        "2、请参考底层错误信息解决(RCVoiceRoomError nativeErrorMessage)"
      ]
    },
    {
      "code": 70026,
      "enMsg": "Accept invitation failed",
      "zhMsg": "同意自定义邀请失败",
      "reasons": [
        "1、请确保已在房间内",
        "2、请参考底层错误信息解决(RCVoiceRoomError nativeErrorMessage)"
      ]
    },
    {
      "code": 70027,
      "enMsg": "Reject invitation failed",
      "zhMsg": "拒绝自定义邀请失败",
      "reasons": [
        "1、请确保已在房间内",
        "2、请参考底层错误信息解决(RCVoiceRoomError nativeErrorMessage)"
      ]
    },
    {
      "code": 70028,
      "enMsg": "Create room failed",
      "zhMsg": "房间创建失败",
      "reasons": [
        "1、请参考底层错误信息解决(RCVoiceRoomError nativeErrorMessage)"
      ]
    },
    {
      "code": 70029,
      "enMsg": "User id is empty",
      "zhMsg": "当前用户登录或连接异常",
      "reasons": [
        "1、请检查IM是否初始化和连接融云服务成功",
        "2、检查joinRoom或createAndJoinroom是否因异步或其他原因导致在连接成功前触发"
      ]
    },
    {
      "code": 70030,
      "enMsg": "Get latest seat info failed",
      "zhMsg": "获取最新麦位列表失败",
      "reasons": [
        "1、请确保已在房间内",
        "2、请参考底层错误信息解决(RCVoiceRoomError nativeErrorMessage)"
      ]
    },
    {
      "code": 70031,
      "enMsg": "Pk begin failed",
      "zhMsg": "开始Pk失败",
      "reasons": [
        "1、请确保pk双方是否都正在各自的房间内，且是主播角色",
        "2、请参考底层错误信息解决(RCVoiceRoomError nativeErrorMessage)"
      ]
    },
    {
      "code": 70032,
      "enMsg": "Pk quit failed",
      "zhMsg": "结束PK失败",
      "reasons": [
        "1、请确保当前已开始PK",
        "2、请确保当前是开始pk后首次quitPK()，重复退出pk会异常",
        "3、请确保因为PK双方只有一方执行了quitPK()",
        "退出成功回触发PK的另一方执行quitPK",
        "如双发都执行会导致后执行quitPK()的一方实际执行两次退出而报错",
        "4、请参考底层错误信息解决(RCVoiceRoomError nativeErrorMessage)"
      ]
    },
    {
      "code": 70033,
      "enMsg": "Pk invitation failed",
      "zhMsg": "发起PK失败",
      "reasons": [
        "1、请确保当前已加入房间，且是主播角色",
        "2、请参考底层错误信息解决(RCVoiceRoomError nativeErrorMessage)"
      ]
    },
    {
      "code": 70034,
      "enMsg": "Cancel pk invitation failed",
      "zhMsg": "取消PK邀请失败",
      "reasons": [
        "1、请确保当前已加入房间，且是主播角色",
        "2、请参考底层错误信息解决(RCVoiceRoomError nativeErrorMessage)"
      ]
    },
    {
      "code": 70035,
      "enMsg": "Mute pk user failed",
      "zhMsg": "pk中关闭对方的音频失败",
      "reasons": [
        "1、请确保当前已开始PK",
        "2、请参考底层错误信息解决(RCVoiceRoomError nativeErrorMessage)"
      ]
    },
    {
      "code": 70036,
      "enMsg": "Room name or seat count not empty",
      "zhMsg": "房间信息不完善",
      "reasons": [
        "1、请确保房间ID不为空",
        "2、请确保房间名称不为空",
        "3、请确保房间名称不为空，且麦位数seatCount大于0"
      ]
    },
    {
      "code": 70037,
      "enMsg": "Already in pk",
      "zhMsg": "正在PK",
      "reasons": []
    },
    {
      "code": 70038,
      "enMsg": "Switch role failed",
      "zhMsg": "切换角色错误",
      "reasons": [
        "1、当前用户的上麦、下麦都会触发用户角色变更",
        "2、请参考底层错误信息解决(RCVoiceRoomError nativeErrorMessage)"
      ]
    },
    {
      "code": 70039,
      "enMsg": "Mute others failed",
      "zhMsg": "静音/取消静音 其他所有麦位失败",
      "reasons": [
        "1、麦位信息未全部更新成功，稍后重试",
        "2、请参考底层错误信息解决(RCVoiceRoomError nativeErrorMessage)"
      ]
    },
    {
      "code": 70040,
      "enMsg": "Lock others failed",
      "zhMsg": "锁定/解锁 其他所有麦位失败",
      "reasons": [
        "1、麦位信息未全部更新成功，稍后重试",
        "2、请参考底层错误信息解决(RCVoiceRoomError nativeErrorMessage)"
      ]
    },
    {
      "code": 70041,
      "enMsg": "Pk info check failed",
      "zhMsg": "pk信息检查异常",
      "reasons": [
        "1、请确保pk中发起邀请用户userId和所在房间的roomId非空",
        "2、请确保pk中被邀请的用户的userId和所在房间的roomId非空"
      ]
    },
    {
      "code": 70042,
      "enMsg": "Get role failed",
      "zhMsg": "加入房间是获取当前角色失败",
      "reasons": [
        "1、确保当前房间的roomId非空",
        "2、确保当前房间已通过createAndJoinRoom创建成功",
        "3、请参考底层错误信息解决(RCVoiceRoomError nativeErrorMessage)"
      ]
    },
    {
      "code": 70043,
      "enMsg": "Pk invitation response failed",
      "zhMsg": "响应PK邀请失败",
      "reasons": [
        "1、请确保当前已加入房间，且是主播角色",
        "2、请参考底层错误信息解决(RCVoiceRoomError nativeErrorMessage)"
      ]
    }
  ]
}
